po_yayapf-0.0.2.dist-info/DESCRIPTION.rst
po_yayapf-0.0.2.dist-info/METADATA
po_yayapf-0.0.2.dist-info/RECORD
po_yayapf-0.0.2.dist-info/WHEEL
po_yayapf-0.0.2.dist-info/entry_points.txt
po_yayapf-0.0.2.dist-info/metadata.json
po_yayapf-0.0.2.dist-info/top_level.txt
yayapf/__init__.py
